code_prompt_builder/__init__.py
code_prompt_builder/utils.py
code_prompt_builder-0.0.3.dist-info/LICENSE
code_prompt_builder-0.0.3.dist-info/METADATA
code_prompt_builder-0.0.3.dist-info/WHEEL
code_prompt_builder-0.0.3.dist-info/top_level.txt
code_prompt_builder-0.0.3.dist-info/RECORD
